Metadata-Version: 2.4
Name: llama-index-embeddings-vertex
Version: 0.4.1
Summary: llama-index embeddings vertex integration
Author-email: Henry Jiang <h243jian@uwaterloo.ca>
License-Expression: MIT
License-File: LICENSE
Requires-Python: <4.0,>=3.9
Requires-Dist: google-cloud-aiplatform>=1.43.0
Requires-Dist: llama-index-core<0.15,>=0.13.0
